{
   "agent": "gws",
   "behavior": "OK",
   "behaviorClose": "OK",
   "case": 351,
   "closedByMe": true,
   "createStats": true,
   "createWirelog": true,
   "description": "Send 1000 compressed messages each of payload size 65536, auto-fragment to 256 octets. Use default permessage-deflate offer.",
   "droppedByMe": false,
   "duration": 6198,
   "expectation": "Receive echo'ed messages (with payload as sent). Timeout case after 480 secs.",
   "expected": {},
   "expectedClose": {
      "closeCode": [
         1000
      ],
      "closedByMe": true,
      "requireClean": true
   },
   "failedByMe": false,
   "httpRequest": "GET /connect HTTP/1.1\r\nUser-Agent: AutobahnTestSuite/0.8.2-0.10.9\r\nHost: 192.168.31.98:3000\r\nUpgrade: WebSocket\r\nConnection: Upgrade\r\nPragma: no-cache\r\nCache-Control: no-cache\r\nSec-WebSocket-Key: p7xRSSIi8qWXdDVatnXyaA==\r\nSec-WebSocket-Extensions: permessage-deflate; client_no_context_takeover; client_max_window_bits\r\nSec-WebSocket-Version: 13\r\n\r\n",
   "httpResponse": "HTTP/1.1 101 Switching Protocols\r\nUpgrade: websocket\r\nConnection: Upgrade\r\nSec-WebSocket-Accept: Yppr2nhCEA9uhU6tc+X4P0NaHRU=\r\nSec-Websocket-Extensions: permessage-deflate; server_no_context_takeover; client_no_context_takeover\r\n\r\n",
   "id": "12.3.14",
   "isServer": false,
   "localCloseCode": 1000,
   "localCloseReason": null,
   "received": [],
   "remoteCloseCode": 1000,
   "remoteCloseReason": null,
   "reportCompressionRatio": true,
   "reportTime": true,
   "result": "Ok, received all echo'ed messages in time.",
   "resultClose": "Connection was properly closed",
   "rxFrameStats": {
      "2": 1000,
      "8": 1
   },
   "rxOctetStats": {
      "4": 1,
      "231": 1,
      "14480": 1,
      "16481": 1,
      "29726": 1,
      "29742": 1,
      "29743": 2,
      "29746": 1,
      "29748": 2,
      "29751": 2,
      "29753": 1,
      "29757": 1,
      "29758": 1,
      "29759": 1,
      "29762": 1,
      "29764": 1,
      "29768": 2,
      "29769": 2,
      "29771": 1,
      "29772": 2,
      "29773": 1,
      "29779": 1,
      "29780": 1,
      "29781": 1,
      "29782": 2,
      "29783": 1,
      "29785": 1,
      "29786": 1,
      "29787": 1,
      "29788": 1,
      "29789": 1,
      "29790": 2,
      "29791": 1,
      "29793": 1,
      "29794": 1,
      "29796": 2,
      "29797": 1,
      "29798": 3,
      "29799": 1,
      "29800": 1,
      "29801": 2,
      "29802": 1,
      "29803": 1,
      "29805": 1,
      "29807": 1,
      "29812": 2,
      "29814": 1,
      "29815": 1,
      "29816": 2,
      "29817": 1,
      "29818": 3,
      "29821": 1,
      "29824": 1,
      "29829": 1,
      "29833": 2,
      "29834": 2,
      "29837": 1,
      "29838": 1,
      "29839": 2,
      "29840": 1,
      "29841": 1,
      "29843": 1,
      "29844": 1,
      "29846": 1,
      "29847": 1,
      "29848": 3,
      "29850": 1,
      "29851": 2,
      "29853": 1,
      "29854": 1,
      "29856": 4,
      "29859": 1,
      "29860": 1,
      "29861": 1,
      "29864": 1,
      "29868": 1,
      "29869": 2,
      "29870": 1,
      "29871": 3,
      "29872": 1,
      "29873": 1,
      "29874": 1,
      "29875": 2,
      "29880": 1,
      "29883": 2,
      "29886": 2,
      "29888": 1,
      "29890": 1,
      "29891": 2,
      "29892": 1,
      "29895": 2,
      "29896": 2,
      "29900": 3,
      "29901": 1,
      "29903": 1,
      "29904": 1,
      "29906": 3,
      "29907": 1,
      "29910": 2,
      "29911": 2,
      "29913": 1,
      "29914": 1,
      "29915": 2,
      "29917": 1,
      "29918": 2,
      "29920": 2,
      "29921": 2,
      "29922": 1,
      "29923": 1,
      "29924": 1,
      "29925": 2,
      "29926": 1,
      "29927": 1,
      "29934": 1,
      "29935": 2,
      "29937": 1,
      "29938": 2,
      "29940": 3,
      "29941": 2,
      "29942": 1,
      "29945": 1,
      "29947": 2,
      "29948": 1,
      "29949": 3,
      "29950": 2,
      "29951": 3,
      "29952": 2,
      "29955": 2,
      "29956": 1,
      "29957": 1,
      "29959": 2,
      "29960": 1,
      "29961": 1,
      "29962": 3,
      "29963": 2,
      "29964": 1,
      "29965": 1,
      "29968": 1,
      "29969": 2,
      "29971": 1,
      "29972": 1,
      "29974": 1,
      "29977": 2,
      "29978": 1,
      "29979": 1,
      "29982": 1,
      "29983": 3,
      "29984": 2,
      "29985": 2,
      "29987": 1,
      "29988": 1,
      "29989": 1,
      "29990": 2,
      "29991": 1,
      "29992": 1,
      "29993": 3,
      "29994": 2,
      "29996": 3,
      "29997": 1,
      "29998": 1,
      "29999": 2,
      "30000": 1,
      "30001": 2,
      "30002": 2,
      "30006": 1,
      "30008": 5,
      "30009": 2,
      "30012": 3,
      "30015": 2,
      "30017": 1,
      "30018": 1,
      "30019": 3,
      "30021": 1,
      "30022": 3,
      "30025": 1,
      "30026": 3,
      "30027": 2,
      "30028": 3,
      "30029": 2,
      "30030": 1,
      "30031": 2,
      "30032": 2,
      "30033": 1,
      "30035": 2,
      "30036": 5,
      "30037": 1,
      "30038": 1,
      "30039": 1,
      "30042": 3,
      "30043": 1,
      "30044": 2,
      "30045": 4,
      "30046": 3,
      "30048": 1,
      "30049": 4,
      "30051": 1,
      "30052": 1,
      "30053": 5,
      "30055": 3,
      "30056": 1,
      "30058": 4,
      "30059": 5,
      "30060": 4,
      "30061": 3,
      "30062": 3,
      "30063": 1,
      "30064": 1,
      "30065": 5,
      "30067": 3,
      "30068": 3,
      "30069": 2,
      "30070": 1,
      "30071": 3,
      "30073": 5,
      "30074": 2,
      "30075": 2,
      "30076": 2,
      "30077": 7,
      "30078": 4,
      "30079": 2,
      "30080": 1,
      "30081": 1,
      "30082": 3,
      "30083": 2,
      "30084": 3,
      "30085": 1,
      "30086": 3,
      "30087": 1,
      "30089": 6,
      "30090": 1,
      "30091": 2,
      "30092": 3,
      "30093": 3,
      "30094": 3,
      "30095": 1,
      "30096": 3,
      "30097": 3,
      "30099": 2,
      "30100": 1,
      "30101": 4,
      "30102": 7,
      "30104": 4,
      "30105": 2,
      "30106": 3,
      "30107": 6,
      "30108": 2,
      "30109": 8,
      "30110": 4,
      "30111": 2,
      "30112": 4,
      "30113": 1,
      "30114": 2,
      "30115": 6,
      "30116": 2,
      "30117": 5,
      "30118": 1,
      "30119": 3,
      "30120": 5,
      "30121": 3,
      "30122": 2,
      "30123": 2,
      "30124": 2,
      "30125": 1,
      "30127": 2,
      "30128": 2,
      "30129": 2,
      "30130": 1,
      "30131": 4,
      "30132": 3,
      "30133": 2,
      "30135": 5,
      "30136": 3,
      "30137": 3,
      "30138": 1,
      "30140": 1,
      "30141": 3,
      "30142": 3,
      "30143": 3,
      "30145": 2,
      "30146": 1,
      "30147": 2,
      "30149": 2,
      "30150": 2,
      "30151": 2,
      "30152": 2,
      "30153": 2,
      "30155": 3,
      "30156": 2,
      "30157": 1,
      "30159": 1,
      "30160": 1,
      "30163": 1,
      "30164": 1,
      "30165": 1,
      "30166": 1,
      "30167": 1,
      "30168": 4,
      "30173": 3,
      "30174": 2,
      "30175": 1,
      "30176": 2,
      "30177": 1,
      "30179": 2,
      "30180": 1,
      "30181": 1,
      "30182": 2,
      "30183": 2,
      "30184": 1,
      "30185": 2,
      "30186": 2,
      "30187": 3,
      "30188": 2,
      "30189": 2,
      "30190": 1,
      "30192": 1,
      "30194": 5,
      "30199": 1,
      "30200": 2,
      "30201": 1,
      "30202": 1,
      "30204": 2,
      "30205": 1,
      "30206": 3,
      "30209": 2,
      "30210": 1,
      "30212": 2,
      "30213": 1,
      "30214": 2,
      "30218": 1,
      "30219": 1,
      "30220": 1,
      "30222": 1,
      "30226": 1,
      "30228": 1,
      "30229": 2,
      "30232": 1,
      "30234": 1,
      "30237": 2,
      "30238": 1,
      "30239": 1,
      "30240": 2,
      "30241": 1,
      "30242": 1,
      "30243": 1,
      "30247": 2,
      "30248": 1,
      "30253": 3,
      "30254": 1,
      "30261": 1,
      "30262": 3,
      "30265": 1,
      "30267": 1,
      "30268": 1,
      "30269": 2,
      "30270": 2,
      "30275": 1,
      "30277": 1,
      "30279": 1,
      "30282": 1,
      "30284": 1,
      "30286": 2,
      "30289": 1,
      "30291": 2,
      "30293": 1,
      "30294": 1,
      "30298": 1,
      "30299": 1,
      "30300": 1,
      "30301": 1,
      "30305": 1,
      "30312": 1,
      "30314": 1,
      "30316": 1,
      "30317": 1,
      "30319": 1,
      "30320": 1,
      "30323": 1,
      "30326": 5,
      "30327": 1,
      "30328": 1,
      "30329": 1,
      "30330": 1,
      "30333": 1,
      "30338": 1,
      "30344": 1,
      "30345": 1,
      "30352": 1,
      "30353": 1,
      "30365": 1,
      "30366": 1,
      "30370": 1,
      "30378": 1,
      "30380": 1,
      "30383": 1,
      "30387": 1,
      "30390": 1,
      "30398": 1,
      "30402": 1,
      "30403": 1,
      "30404": 1,
      "30405": 1,
      "30407": 1,
      "30410": 1,
      "30412": 1,
      "30416": 1,
      "30418": 1,
      "30419": 1,
      "30420": 2,
      "30421": 1,
      "30423": 1,
      "30424": 2,
      "30427": 1,
      "30429": 1,
      "30430": 1,
      "30431": 3,
      "30433": 1,
      "30434": 1,
      "30437": 1,
      "30439": 2,
      "30440": 2,
      "30441": 2,
      "30442": 1,
      "30444": 3,
      "30445": 2,
      "30447": 2,
      "30448": 1,
      "30449": 2,
      "30450": 1,
      "30452": 1,
      "30456": 4,
      "30458": 1,
      "30459": 3,
      "30460": 1,
      "30462": 2,
      "30463": 2,
      "30465": 1,
      "30467": 1,
      "30469": 1,
      "30472": 1,
      "30475": 1,
      "30477": 1,
      "30486": 1,
      "30493": 2,
      "30494": 1,
      "30498": 1,
      "30501": 1,
      "30502": 1,
      "30507": 1,
      "30512": 2,
      "30513": 2,
      "30514": 1,
      "30515": 1,
      "30519": 1,
      "30523": 1,
      "30524": 1,
      "30529": 1,
      "30531": 1,
      "30537": 1,
      "30541": 1,
      "30542": 1,
      "30546": 1,
      "30549": 2,
      "30550": 2,
      "30552": 1,
      "30553": 1,
      "30554": 1,
      "30555": 1,
      "30557": 3,
      "30558": 1,
      "30563": 1,
      "30564": 1,
      "30565": 1,
      "30567": 1,
      "30571": 3,
      "30573": 2,
      "30574": 1,
      "30575": 2,
      "30576": 1,
      "30577": 1,
      "30579": 2,
      "30581": 2,
      "30583": 1,
      "30585": 1,
      "30588": 3,
      "30591": 1,
      "30593": 1,
      "30594": 2,
      "30596": 1,
      "30597": 1,
      "30598": 3,
      "30599": 1,
      "30600": 1,
      "30603": 1,
      "30604": 2,
      "30605": 2,
      "30607": 1,
      "30608": 1,
      "30609": 4,
      "30610": 1,
      "30611": 1,
      "30615": 2,
      "30617": 1,
      "30620": 1,
      "30624": 1,
      "30625": 1,
      "30627": 1,
      "30630": 2,
      "30634": 3,
      "30635": 1,
      "30641": 1,
      "30645": 3,
      "30646": 1,
      "30647": 1,
      "30649": 2,
      "30655": 1,
      "30659": 1,
      "30660": 1,
      "30664": 1,
      "30667": 1,
      "30671": 2,
      "30673": 1,
      "30675": 1,
      "30676": 1,
      "30678": 1,
      "30680": 1,
      "30683": 2,
      "30684": 2,
      "30685": 1,
      "30688": 1,
      "30689": 1,
      "30692": 2,
      "30693": 1,
      "30697": 2,
      "30702": 1,
      "30706": 2,
      "30711": 1,
      "30713": 1,
      "30720": 1,
      "30721": 1,
      "30730": 1,
      "30731": 1,
      "30733": 1,
      "30737": 1,
      "30742": 2,
      "30743": 1,
      "30744": 1,
      "30745": 1,
      "30748": 1,
      "30758": 1,
      "30759": 1,
      "30761": 1,
      "30762": 1,
      "30764": 1,
      "30767": 1,
      "30774": 1,
      "30775": 1,
      "30786": 1,
      "30788": 1,
      "30790": 1,
      "30791": 2,
      "30792": 1,
      "30793": 1,
      "30795": 1,
      "30796": 1,
      "30799": 2,
      "30804": 1,
      "30811": 1,
      "30827": 2,
      "30830": 1,
      "30834": 1,
      "30835": 1,
      "30843": 1,
      "30845": 1,
      "30848": 1,
      "30856": 1,
      "30878": 1,
      "30902": 1,
      "30934": 1,
      "30938": 1,
      "30946": 1,
      "30954": 1,
      "30955": 1,
      "30958": 1,
      "30966": 1,
      "30988": 1,
      "31002": 1,
      "31003": 1,
      "31005": 2,
      "31007": 2,
      "31009": 3,
      "31011": 1,
      "31013": 1,
      "31014": 2,
      "31015": 1,
      "31017": 1,
      "31018": 2,
      "31019": 1,
      "31021": 1,
      "31022": 1,
      "31028": 2,
      "31033": 2,
      "31040": 1,
      "31066": 1,
      "31068": 1,
      "31069": 1,
      "31073": 1,
      "31079": 1,
      "31085": 1,
      "31102": 2,
      "31105": 1,
      "31110": 1,
      "31132": 1,
      "31137": 1,
      "31163": 1,
      "31203": 1,
      "31272": 1,
      "31528": 1
   },
   "started": "2023-04-29T06:02:03.443Z",
   "trafficStats": {
      "incomingCompressionRatio": 0.46124082946777345,
      "incomingOctetsAppLevel": 65536000,
      "incomingOctetsWebSocketLevel": 30227879,
      "incomingOctetsWireLevel": 30231879,
      "incomingWebSocketFrames": 1000,
      "incomingWebSocketMessages": 1000,
      "incomingWebSocketOverhead": 0.00013232817294260045,
      "outgoingCompressionRatio": 0.4012429504394531,
      "outgoingOctetsAppLevel": 65536000,
      "outgoingOctetsWebSocketLevel": 26295858,
      "outgoingOctetsWireLevel": 27120774,
      "outgoingWebSocketFrames": 103246,
      "outgoingWebSocketMessages": 1000,
      "outgoingWebSocketOverhead": 0.031370567942677514,
      "preopenIncomingOctetsWireLevel": 231,
      "preopenOutgoingOctetsWireLevel": 349
   },
   "txFrameStats": {
      "0": 102246,
      "2": 1000,
      "8": 1
   },
   "txOctetStats": {
      "6": 4,
      "7": 3,
      "8": 4,
      "9": 2,
      "10": 4,
      "11": 4,
      "12": 4,
      "13": 4,
      "14": 5,
      "15": 7,
      "16": 4,
      "17": 4,
      "18": 11,
      "19": 4,
      "20": 5,
      "21": 2,
      "22": 5,
      "24": 2,
      "25": 6,
      "26": 2,
      "27": 6,
      "28": 4,
      "29": 3,
      "30": 9,
      "31": 6,
      "32": 9,
      "33": 2,
      "34": 6,
      "35": 5,
      "36": 3,
      "37": 6,
      "38": 4,
      "39": 7,
      "40": 5,
      "41": 4,
      "42": 4,
      "43": 2,
      "44": 5,
      "45": 3,
      "46": 8,
      "47": 1,
      "48": 5,
      "49": 8,
      "50": 5,
      "51": 4,
      "52": 3,
      "53": 2,
      "54": 8,
      "55": 3,
      "56": 4,
      "57": 8,
      "58": 4,
      "59": 4,
      "60": 4,
      "61": 6,
      "62": 2,
      "63": 6,
      "64": 2,
      "65": 4,
      "66": 5,
      "67": 2,
      "68": 2,
      "69": 9,
      "70": 2,
      "71": 4,
      "72": 6,
      "73": 2,
      "74": 4,
      "75": 5,
      "76": 1,
      "77": 6,
      "78": 5,
      "79": 4,
      "80": 7,
      "81": 3,
      "82": 6,
      "83": 2,
      "84": 5,
      "85": 4,
      "86": 3,
      "87": 1,
      "88": 4,
      "89": 4,
      "90": 3,
      "91": 3,
      "92": 2,
      "93": 5,
      "94": 1,
      "95": 4,
      "96": 3,
      "97": 1,
      "98": 5,
      "99": 4,
      "100": 2,
      "101": 5,
      "102": 5,
      "103": 5,
      "104": 4,
      "105": 3,
      "106": 10,
      "107": 7,
      "108": 6,
      "109": 2,
      "111": 4,
      "112": 1,
      "113": 3,
      "114": 5,
      "115": 4,
      "117": 5,
      "118": 4,
      "119": 3,
      "120": 3,
      "121": 1,
      "122": 5,
      "123": 4,
      "124": 6,
      "125": 5,
      "126": 1,
      "127": 3,
      "128": 5,
      "129": 8,
      "130": 6,
      "131": 5,
      "134": 2,
      "135": 2,
      "136": 7,
      "137": 6,
      "138": 4,
      "139": 8,
      "140": 3,
      "141": 5,
      "142": 2,
      "143": 4,
      "144": 4,
      "145": 2,
      "146": 8,
      "147": 4,
      "148": 4,
      "149": 4,
      "150": 4,
      "151": 3,
      "152": 3,
      "153": 6,
      "154": 2,
      "155": 4,
      "156": 3,
      "157": 5,
      "158": 7,
      "159": 3,
      "160": 6,
      "161": 3,
      "162": 2,
      "163": 2,
      "164": 3,
      "165": 4,
      "166": 4,
      "167": 8,
      "168": 6,
      "169": 2,
      "170": 8,
      "171": 1,
      "172": 2,
      "173": 5,
      "174": 4,
      "175": 4,
      "176": 4,
      "177": 1,
      "178": 1,
      "179": 4,
      "180": 2,
      "181": 4,
      "182": 1,
      "183": 1,
      "184": 4,
      "185": 4,
      "187": 6,
      "188": 2,
      "189": 4,
      "190": 3,
      "191": 4,
      "192": 3,
      "193": 2,
      "194": 2,
      "195": 2,
      "196": 6,
      "197": 1,
      "198": 4,
      "199": 5,
      "200": 4,
      "201": 5,
      "202": 7,
      "203": 7,
      "204": 5,
      "205": 6,
      "206": 3,
      "207": 2,
      "208": 4,
      "209": 3,
      "210": 4,
      "211": 1,
      "212": 3,
      "213": 3,
      "214": 2,
      "215": 6,
      "216": 3,
      "217": 4,
      "218": 7,
      "219": 3,
      "220": 4,
      "221": 3,
      "222": 5,
      "223": 5,
      "224": 5,
      "225": 3,
      "226": 6,
      "227": 4,
      "228": 1,
      "229": 4,
      "230": 3,
      "231": 2,
      "232": 6,
      "233": 3,
      "234": 2,
      "235": 3,
      "236": 4,
      "237": 2,
      "238": 6,
      "239": 2,
      "240": 3,
      "241": 4,
      "242": 2,
      "243": 4,
      "245": 3,
      "246": 5,
      "247": 2,
      "248": 6,
      "249": 2,
      "250": 6,
      "251": 2,
      "252": 7,
      "253": 3,
      "254": 2,
      "255": 3,
      "256": 1,
      "257": 4,
      "258": 4,
      "259": 1,
      "260": 3,
      "261": 2,
      "262": 5,
      "263": 2,
      "264": 102246,
      "349": 1
   },
   "wasClean": true,
   "wasCloseHandshakeTimeout": false,
   "wasNotCleanReason": null,
   "wasOpenHandshakeTimeout": false,
   "wasServerConnectionDropTimeout": false,
   "wirelog": [
      [
         "TO",
         [
            349,
            "474554202f636f6e6e65637420485454502f312e310d0a557365722d4167656e743a204175746f6261686e5465737453756974652f302e382e322d302e31302e ..."
         ],
         false
      ],
      [
         "RO",
         [
            231,
            "485454502f312e312031303120537769746368696e672050726f746f636f6c730d0a557067726164653a20776562736f636b65740d0a436f6e6e656374696f6e ..."
         ]
      ],
      [
         "WLM",
         false
      ],
      [
         "TI",
         480
      ],
      [
         "WLM",
         true
      ],
      [
         "TF",
         [
            2,
            "0x03e8"
         ],
         8,
         true,
         0,
         "d346fa0b",
         null,
         null,
         false
      ],
      [
         "TO",
         [
            8,
            "8882d346fa0bd0ae"
         ],
         false
      ],
      [
         "RO",
         [
            4,
            "880203e8"
         ]
      ],
      [
         "RF",
         [
            2,
            "0x03e8"
         ],
         8,
         true,
         0,
         false,
         null
      ]
   ]
}