{
   "agent": "gws-server/async/context_take_over",
   "behavior": "OK",
   "behaviorClose": "OK",
   "case": 301,
   "closedByMe": true,
   "createStats": true,
   "createWirelog": true,
   "description": "Send text message with payload of length 65536 auto-fragmented with <b>autoFragmentSize = 1300</b>.",
   "droppedByMe": false,
   "duration": 4,
   "expectation": "Receive echo'ed text message (with payload as sent and transmitted frame counts as expected). Clean close with normal code.",
   "expected": {
      "OK": [
         [
            "message",
            "**************************************************************** ...",
            false
         ]
      ]
   },
   "expectedClose": {
      "closeCode": [
         1000
      ],
      "closedByMe": true,
      "requireClean": true
   },
   "failedByMe": false,
   "httpRequest": "GET /connect HTTP/1.1\r\nUser-Agent: AutobahnTestSuite/0.8.2-0.10.9\r\nHost: 127.0.0.1:8001\r\nUpgrade: WebSocket\r\nConnection: Upgrade\r\nPragma: no-cache\r\nCache-Control: no-cache\r\nSec-WebSocket-Key: qn9iu36MbeNujIYHpbuf1g==\r\nSec-WebSocket-Version: 13\r\n\r\n",
   "httpResponse": "HTTP/1.1 101 Switching Protocols\r\nUpgrade: websocket\r\nConnection: Upgrade\r\nSec-WebSocket-Accept: S3uHBMyXfjRNV1XjYcZfJ/qQeKk=\r\n\r\n",
   "id": "10.1.1",
   "isServer": false,
   "localCloseCode": 1000,
   "localCloseReason": null,
   "received": [
      [
         "message",
         "**************************************************************** ...",
         false
      ]
   ],
   "remoteCloseCode": 1000,
   "remoteCloseReason": null,
   "reportCompressionRatio": false,
   "reportTime": false,
   "result": "Actual events match at least one expected.",
   "resultClose": "Connection was properly closed",
   "rxFrameStats": {
      "1": 1,
      "8": 1
   },
   "rxOctetStats": {
      "4": 1,
      "10": 1,
      "129": 1,
      "65536": 1
   },
   "started": "2024-01-18T07:38:47.158Z",
   "trafficStats": null,
   "txFrameStats": {
      "0": 50,
      "1": 1,
      "8": 1
   },
   "txOctetStats": {
      "8": 1,
      "247": 1,
      "544": 1,
      "1308": 50
   },
   "wasClean": true,
   "wasCloseHandshakeTimeout": false,
   "wasNotCleanReason": null,
   "wasOpenHandshakeTimeout": false,
   "wasServerConnectionDropTimeout": false,
   "wirelog": [
      [
         "TO",
         [
            247,
            "474554202f636f6e6e65637420485454502f312e310d0a557365722d4167656e743a204175746f6261686e5465737453756974652f302e382e322d302e31302e ..."
         ],
         false
      ],
      [
         "RO",
         [
            129,
            "485454502f312e312031303120537769746368696e672050726f746f636f6c730d0a557067726164653a20776562736f636b65740d0a436f6e6e656374696f6e ..."
         ]
      ],
      [
         "TF",
         [
            1300,
            "**************************************************************** ..."
         ],
         1,
         false,
         0,
         "25596727",
         null,
         null,
         false
      ],
      [
         "TO",
         [
            1308,
            "01fe0514255967270f734d0d0f734d0d0f734d0d0f734d0d0f734d0d0f734d0d0f734d0d0f734d0d0f734d0d0f734d0d0f734d0d0f734d0d0f734d0d0f734d0d ..."
         ],
         false
      ],
      [
         "TF",
         [
            1300,
            "**************************************************************** ..."
         ],
         0,
         false,
         0,
         "49d7de87",
         null,
         null,
         false
      ],
      [
         "TO",
         [
            1308,
            "00fe051449d7de8763fdf4ad63fdf4ad63fdf4ad63fdf4ad63fdf4ad63fdf4ad63fdf4ad63fdf4ad63fdf4ad63fdf4ad63fdf4ad63fdf4ad63fdf4ad63fdf4ad ..."
         ],
         false
      ],
      [
         "TF",
         [
            1300,
            "**************************************************************** ..."
         ],
         0,
         false,
         0,
         "3431b12b",
         null,
         null,
         false
      ],
      [
         "TO",
         [
            1308,
            "00fe05143431b12b1e1b9b011e1b9b011e1b9b011e1b9b011e1b9b011e1b9b011e1b9b011e1b9b011e1b9b011e1b9b011e1b9b011e1b9b011e1b9b011e1b9b01 ..."
         ],
         false
      ],
      [
         "TF",
         [
            1300,
            "**************************************************************** ..."
         ],
         0,
         false,
         0,
         "4a8aa33c",
         null,
         null,
         false
      ],
      [
         "TO",
         [
            1308,
            "00fe05144a8aa33c60a0891660a0891660a0891660a0891660a0891660a0891660a0891660a0891660a0891660a0891660a0891660a0891660a0891660a08916 ..."
         ],
         false
      ],
      [
         "TF",
         [
            1300,
            "**************************************************************** ..."
         ],
         0,
         false,
         0,
         "1e641b60",
         null,
         null,
         false
      ],
      [
         "TO",
         [
            1308,
            "00fe05141e641b60344e314a344e314a344e314a344e314a344e314a344e314a344e314a344e314a344e314a344e314a344e314a344e314a344e314a344e314a ..."
         ],
         false
      ],
      [
         "TF",
         [
            1300,
            "**************************************************************** ..."
         ],
         0,
         false,
         0,
         "3a9e04fb",
         null,
         null,
         false
      ],
      [
         "TO",
         [
            1308,
            "00fe05143a9e04fb10b42ed110b42ed110b42ed110b42ed110b42ed110b42ed110b42ed110b42ed110b42ed110b42ed110b42ed110b42ed110b42ed110b42ed1 ..."
         ],
         false
      ],
      [
         "TF",
         [
            1300,
            "**************************************************************** ..."
         ],
         0,
         false,
         0,
         "897d309e",
         null,
         null,
         false
      ],
      [
         "TO",
         [
            1308,
            "00fe0514897d309ea3571ab4a3571ab4a3571ab4a3571ab4a3571ab4a3571ab4a3571ab4a3571ab4a3571ab4a3571ab4a3571ab4a3571ab4a3571ab4a3571ab4 ..."
         ],
         false
      ],
      [
         "TF",
         [
            1300,
            "**************************************************************** ..."
         ],
         0,
         false,
         0,
         "3c7f0328",
         null,
         null,
         false
      ],
      [
         "TO",
         [
            1308,
            "00fe05143c7f03281655290216552902165529021655290216552902165529021655290216552902165529021655290216552902165529021655290216552902 ..."
         ],
         false
      ],
      [
         "TF",
         [
            1300,
            "**************************************************************** ..."
         ],
         0,
         false,
         0,
         "8f81b116",
         null,
         null,
         false
      ],
      [
         "TO",
         [
            1308,
            "00fe05148f81b116a5ab9b3ca5ab9b3ca5ab9b3ca5ab9b3ca5ab9b3ca5ab9b3ca5ab9b3ca5ab9b3ca5ab9b3ca5ab9b3ca5ab9b3ca5ab9b3ca5ab9b3ca5ab9b3c ..."
         ],
         false
      ],
      [
         "TF",
         [
            1300,
            "**************************************************************** ..."
         ],
         0,
         false,
         0,
         "ffa5dab7",
         null,
         null,
         false
      ],
      [
         "TO",
         [
            1308,
            "00fe0514ffa5dab7d58ff09dd58ff09dd58ff09dd58ff09dd58ff09dd58ff09dd58ff09dd58ff09dd58ff09dd58ff09dd58ff09dd58ff09dd58ff09dd58ff09d ..."
         ],
         false
      ],
      [
         "TF",
         [
            1300,
            "**************************************************************** ..."
         ],
         0,
         false,
         0,
         "a3d58f44",
         null,
         null,
         false
      ],
      [
         "TO",
         [
            1308,
            "00fe0514a3d58f4489ffa56e89ffa56e89ffa56e89ffa56e89ffa56e89ffa56e89ffa56e89ffa56e89ffa56e89ffa56e89ffa56e89ffa56e89ffa56e89ffa56e ..."
         ],
         false
      ],
      [
         "TF",
         [
            1300,
            "**************************************************************** ..."
         ],
         0,
         false,
         0,
         "b8570099",
         null,
         null,
         false
      ],
      [
         "TO",
         [
            1308,
            "00fe0514b8570099927d2ab3927d2ab3927d2ab3927d2ab3927d2ab3927d2ab3927d2ab3927d2ab3927d2ab3927d2ab3927d2ab3927d2ab3927d2ab3927d2ab3 ..."
         ],
         false
      ],
      [
         "TF",
         [
            1300,
            "**************************************************************** ..."
         ],
         0,
         false,
         0,
         "b9c4e9df",
         null,
         null,
         false
      ],
      [
         "TO",
         [
            1308,
            "00fe0514b9c4e9df93eec3f593eec3f593eec3f593eec3f593eec3f593eec3f593eec3f593eec3f593eec3f593eec3f593eec3f593eec3f593eec3f593eec3f5 ..."
         ],
         false
      ],
      [
         "TF",
         [
            1300,
            "**************************************************************** ..."
         ],
         0,
         false,
         0,
         "1804c65c",
         null,
         null,
         false
      ],
      [
         "TO",
         [
            1308,
            "00fe05141804c65c322eec76322eec76322eec76322eec76322eec76322eec76322eec76322eec76322eec76322eec76322eec76322eec76322eec76322eec76 ..."
         ],
         false
      ],
      [
         "TF",
         [
            1300,
            "**************************************************************** ..."
         ],
         0,
         false,
         0,
         "8904adc6",
         null,
         null,
         false
      ],
      [
         "TO",
         [
            1308,
            "00fe05148904adc6a32e87eca32e87eca32e87eca32e87eca32e87eca32e87eca32e87eca32e87eca32e87eca32e87eca32e87eca32e87eca32e87eca32e87ec ..."
         ],
         false
      ],
      [
         "TF",
         [
            1300,
            "**************************************************************** ..."
         ],
         0,
         false,
         0,
         "cea2b289",
         null,
         null,
         false
      ],
      [
         "TO",
         [
            1308,
            "00fe0514cea2b289e48898a3e48898a3e48898a3e48898a3e48898a3e48898a3e48898a3e48898a3e48898a3e48898a3e48898a3e48898a3e48898a3e48898a3 ..."
         ],
         false
      ],
      [
         "TF",
         [
            1300,
            "**************************************************************** ..."
         ],
         0,
         false,
         0,
         "c6aa9b5f",
         null,
         null,
         false
      ],
      [
         "TO",
         [
            1308,
            "00fe0514c6aa9b5fec80b175ec80b175ec80b175ec80b175ec80b175ec80b175ec80b175ec80b175ec80b175ec80b175ec80b175ec80b175ec80b175ec80b175 ..."
         ],
         false
      ],
      [
         "TF",
         [
            1300,
            "**************************************************************** ..."
         ],
         0,
         false,
         0,
         "b2d02706",
         null,
         null,
         false
      ],
      [
         "TO",
         [
            1308,
            "00fe0514b2d0270698fa0d2c98fa0d2c98fa0d2c98fa0d2c98fa0d2c98fa0d2c98fa0d2c98fa0d2c98fa0d2c98fa0d2c98fa0d2c98fa0d2c98fa0d2c98fa0d2c ..."
         ],
         false
      ],
      [
         "TF",
         [
            1300,
            "**************************************************************** ..."
         ],
         0,
         false,
         0,
         "48df9627",
         null,
         null,
         false
      ],
      [
         "TO",
         [
            1308,
            "00fe051448df962762f5bc0d62f5bc0d62f5bc0d62f5bc0d62f5bc0d62f5bc0d62f5bc0d62f5bc0d62f5bc0d62f5bc0d62f5bc0d62f5bc0d62f5bc0d62f5bc0d ..."
         ],
         false
      ],
      [
         "TF",
         [
            1300,
            "**************************************************************** ..."
         ],
         0,
         false,
         0,
         "636da8f0",
         null,
         null,
         false
      ],
      [
         "TO",
         [
            1308,
            "00fe0514636da8f0494782da494782da494782da494782da494782da494782da494782da494782da494782da494782da494782da494782da494782da494782da ..."
         ],
         false
      ],
      [
         "TF",
         [
            1300,
            "**************************************************************** ..."
         ],
         0,
         false,
         0,
         "e3ecb19f",
         null,
         null,
         false
      ],
      [
         "TO",
         [
            1308,
            "00fe0514e3ecb19fc9c69bb5c9c69bb5c9c69bb5c9c69bb5c9c69bb5c9c69bb5c9c69bb5c9c69bb5c9c69bb5c9c69bb5c9c69bb5c9c69bb5c9c69bb5c9c69bb5 ..."
         ],
         false
      ],
      [
         "TF",
         [
            1300,
            "**************************************************************** ..."
         ],
         0,
         false,
         0,
         "7f147a2a",
         null,
         null,
         false
      ],
      [
         "TO",
         [
            1308,
            "00fe05147f147a2a553e5000553e5000553e5000553e5000553e5000553e5000553e5000553e5000553e5000553e5000553e5000553e5000553e5000553e5000 ..."
         ],
         false
      ],
      [
         "TF",
         [
            1300,
            "**************************************************************** ..."
         ],
         0,
         false,
         0,
         "146c43fc",
         null,
         null,
         false
      ],
      [
         "TO",
         [
            1308,
            "00fe0514146c43fc3e4669d63e4669d63e4669d63e4669d63e4669d63e4669d63e4669d63e4669d63e4669d63e4669d63e4669d63e4669d63e4669d63e4669d6 ..."
         ],
         false
      ],
      [
         "TF",
         [
            1300,
            "**************************************************************** ..."
         ],
         0,
         false,
         0,
         "90bc0056",
         null,
         null,
         false
      ],
      [
         "TO",
         [
            1308,
            "00fe051490bc0056ba962a7cba962a7cba962a7cba962a7cba962a7cba962a7cba962a7cba962a7cba962a7cba962a7cba962a7cba962a7cba962a7cba962a7c ..."
         ],
         false
      ],
      [
         "TF",
         [
            1300,
            "**************************************************************** ..."
         ],
         0,
         false,
         0,
         "ac95a075",
         null,
         null,
         false
      ],
      [
         "TO",
         [
            1308,
            "00fe0514ac95a07586bf8a5f86bf8a5f86bf8a5f86bf8a5f86bf8a5f86bf8a5f86bf8a5f86bf8a5f86bf8a5f86bf8a5f86bf8a5f86bf8a5f86bf8a5f86bf8a5f ..."
         ],
         false
      ],
      [
         "TF",
         [
            1300,
            "**************************************************************** ..."
         ],
         0,
         false,
         0,
         "b01597dd",
         null,
         null,
         false
      ],
      [
         "TO",
         [
            1308,
            "00fe0514b01597dd9a3fbdf79a3fbdf79a3fbdf79a3fbdf79a3fbdf79a3fbdf79a3fbdf79a3fbdf79a3fbdf79a3fbdf79a3fbdf79a3fbdf79a3fbdf79a3fbdf7 ..."
         ],
         false
      ],
      [
         "TF",
         [
            1300,
            "**************************************************************** ..."
         ],
         0,
         false,
         0,
         "b7a3ed50",
         null,
         null,
         false
      ],
      [
         "TO",
         [
            1308,
            "00fe0514b7a3ed509d89c77a9d89c77a9d89c77a9d89c77a9d89c77a9d89c77a9d89c77a9d89c77a9d89c77a9d89c77a9d89c77a9d89c77a9d89c77a9d89c77a ..."
         ],
         false
      ],
      [
         "TF",
         [
            1300,
            "**************************************************************** ..."
         ],
         0,
         false,
         0,
         "ff409838",
         null,
         null,
         false
      ],
      [
         "TO",
         [
            1308,
            "00fe0514ff409838d56ab212d56ab212d56ab212d56ab212d56ab212d56ab212d56ab212d56ab212d56ab212d56ab212d56ab212d56ab212d56ab212d56ab212 ..."
         ],
         false
      ],
      [
         "TF",
         [
            1300,
            "**************************************************************** ..."
         ],
         0,
         false,
         0,
         "65e3b01a",
         null,
         null,
         false
      ],
      [
         "TO",
         [
            1308,
            "00fe051465e3b01a4fc99a304fc99a304fc99a304fc99a304fc99a304fc99a304fc99a304fc99a304fc99a304fc99a304fc99a304fc99a304fc99a304fc99a30 ..."
         ],
         false
      ],
      [
         "TF",
         [
            1300,
            "**************************************************************** ..."
         ],
         0,
         false,
         0,
         "0ed40703",
         null,
         null,
         false
      ],
      [
         "TO",
         [
            1308,
            "00fe05140ed4070324fe2d2924fe2d2924fe2d2924fe2d2924fe2d2924fe2d2924fe2d2924fe2d2924fe2d2924fe2d2924fe2d2924fe2d2924fe2d2924fe2d29 ..."
         ],
         false
      ],
      [
         "TF",
         [
            1300,
            "**************************************************************** ..."
         ],
         0,
         false,
         0,
         "c3a44e86",
         null,
         null,
         false
      ],
      [
         "TO",
         [
            1308,
            "00fe0514c3a44e86e98e64ace98e64ace98e64ace98e64ace98e64ace98e64ace98e64ace98e64ace98e64ace98e64ace98e64ace98e64ace98e64ace98e64ac ..."
         ],
         false
      ],
      [
         "TF",
         [
            1300,
            "**************************************************************** ..."
         ],
         0,
         false,
         0,
         "d1cde74f",
         null,
         null,
         false
      ],
      [
         "TO",
         [
            1308,
            "00fe0514d1cde74ffbe7cd65fbe7cd65fbe7cd65fbe7cd65fbe7cd65fbe7cd65fbe7cd65fbe7cd65fbe7cd65fbe7cd65fbe7cd65fbe7cd65fbe7cd65fbe7cd65 ..."
         ],
         false
      ],
      [
         "TF",
         [
            1300,
            "**************************************************************** ..."
         ],
         0,
         false,
         0,
         "0374c674",
         null,
         null,
         false
      ],
      [
         "TO",
         [
            1308,
            "00fe05140374c674295eec5e295eec5e295eec5e295eec5e295eec5e295eec5e295eec5e295eec5e295eec5e295eec5e295eec5e295eec5e295eec5e295eec5e ..."
         ],
         false
      ],
      [
         "TF",
         [
            1300,
            "**************************************************************** ..."
         ],
         0,
         false,
         0,
         "a1d46ef8",
         null,
         null,
         false
      ],
      [
         "TO",
         [
            1308,
            "00fe0514a1d46ef88bfe44d28bfe44d28bfe44d28bfe44d28bfe44d28bfe44d28bfe44d28bfe44d28bfe44d28bfe44d28bfe44d28bfe44d28bfe44d28bfe44d2 ..."
         ],
         false
      ],
      [
         "TF",
         [
            1300,
            "**************************************************************** ..."
         ],
         0,
         false,
         0,
         "7a68fb80",
         null,
         null,
         false
      ],
      [
         "TO",
         [
            1308,
            "00fe05147a68fb805042d1aa5042d1aa5042d1aa5042d1aa5042d1aa5042d1aa5042d1aa5042d1aa5042d1aa5042d1aa5042d1aa5042d1aa5042d1aa5042d1aa ..."
         ],
         false
      ],
      [
         "TF",
         [
            1300,
            "**************************************************************** ..."
         ],
         0,
         false,
         0,
         "32a48677",
         null,
         null,
         false
      ],
      [
         "TO",
         [
            1308,
            "00fe051432a48677188eac5d188eac5d188eac5d188eac5d188eac5d188eac5d188eac5d188eac5d188eac5d188eac5d188eac5d188eac5d188eac5d188eac5d ..."
         ],
         false
      ],
      [
         "TF",
         [
            1300,
            "**************************************************************** ..."
         ],
         0,
         false,
         0,
         "f970322d",
         null,
         null,
         false
      ],
      [
         "TO",
         [
            1308,
            "00fe0514f970322dd35a1807d35a1807d35a1807d35a1807d35a1807d35a1807d35a1807d35a1807d35a1807d35a1807d35a1807d35a1807d35a1807d35a1807 ..."
         ],
         false
      ],
      [
         "TF",
         [
            1300,
            "**************************************************************** ..."
         ],
         0,
         false,
         0,
         "437d6e15",
         null,
         null,
         false
      ],
      [
         "TO",
         [
            1308,
            "00fe0514437d6e156957443f6957443f6957443f6957443f6957443f6957443f6957443f6957443f6957443f6957443f6957443f6957443f6957443f6957443f ..."
         ],
         false
      ],
      [
         "TF",
         [
            1300,
            "**************************************************************** ..."
         ],
         0,
         false,
         0,
         "f8859933",
         null,
         null,
         false
      ],
      [
         "TO",
         [
            1308,
            "00fe0514f8859933d2afb319d2afb319d2afb319d2afb319d2afb319d2afb319d2afb319d2afb319d2afb319d2afb319d2afb319d2afb319d2afb319d2afb319 ..."
         ],
         false
      ],
      [
         "TF",
         [
            1300,
            "**************************************************************** ..."
         ],
         0,
         false,
         0,
         "166f5e25",
         null,
         null,
         false
      ],
      [
         "TO",
         [
            1308,
            "00fe0514166f5e253c45740f3c45740f3c45740f3c45740f3c45740f3c45740f3c45740f3c45740f3c45740f3c45740f3c45740f3c45740f3c45740f3c45740f ..."
         ],
         false
      ],
      [
         "TF",
         [
            1300,
            "**************************************************************** ..."
         ],
         0,
         false,
         0,
         "637342de",
         null,
         null,
         false
      ],
      [
         "TO",
         [
            1308,
            "00fe0514637342de495968f4495968f4495968f4495968f4495968f4495968f4495968f4495968f4495968f4495968f4495968f4495968f4495968f4495968f4 ..."
         ],
         false
      ],
      [
         "TF",
         [
            1300,
            "**************************************************************** ..."
         ],
         0,
         false,
         0,
         "a11c2ac7",
         null,
         null,
         false
      ],
      [
         "TO",
         [
            1308,
            "00fe0514a11c2ac78b3600ed8b3600ed8b3600ed8b3600ed8b3600ed8b3600ed8b3600ed8b3600ed8b3600ed8b3600ed8b3600ed8b3600ed8b3600ed8b3600ed ..."
         ],
         false
      ],
      [
         "TF",
         [
            1300,
            "**************************************************************** ..."
         ],
         0,
         false,
         0,
         "71ec3021",
         null,
         null,
         false
      ],
      [
         "TO",
         [
            1308,
            "00fe051471ec30215bc61a0b5bc61a0b5bc61a0b5bc61a0b5bc61a0b5bc61a0b5bc61a0b5bc61a0b5bc61a0b5bc61a0b5bc61a0b5bc61a0b5bc61a0b5bc61a0b ..."
         ],
         false
      ],
      [
         "TF",
         [
            1300,
            "**************************************************************** ..."
         ],
         0,
         false,
         0,
         "26ee7520",
         null,
         null,
         false
      ],
      [
         "TO",
         [
            1308,
            "00fe051426ee75200cc45f0a0cc45f0a0cc45f0a0cc45f0a0cc45f0a0cc45f0a0cc45f0a0cc45f0a0cc45f0a0cc45f0a0cc45f0a0cc45f0a0cc45f0a0cc45f0a ..."
         ],
         false
      ],
      [
         "TF",
         [
            1300,
            "**************************************************************** ..."
         ],
         0,
         false,
         0,
         "cdffd5d2",
         null,
         null,
         false
      ],
      [
         "TO",
         [
            1308,
            "00fe0514cdffd5d2e7d5fff8e7d5fff8e7d5fff8e7d5fff8e7d5fff8e7d5fff8e7d5fff8e7d5fff8e7d5fff8e7d5fff8e7d5fff8e7d5fff8e7d5fff8e7d5fff8 ..."
         ],
         false
      ],
      [
         "TF",
         [
            1300,
            "**************************************************************** ..."
         ],
         0,
         false,
         0,
         "44e65c74",
         null,
         null,
         false
      ],
      [
         "TO",
         [
            1308,
            "00fe051444e65c746ecc765e6ecc765e6ecc765e6ecc765e6ecc765e6ecc765e6ecc765e6ecc765e6ecc765e6ecc765e6ecc765e6ecc765e6ecc765e6ecc765e ..."
         ],
         false
      ],
      [
         "TF",
         [
            1300,
            "**************************************************************** ..."
         ],
         0,
         false,
         0,
         "e44f7877",
         null,
         null,
         false
      ],
      [
         "TO",
         [
            1308,
            "00fe0514e44f7877ce65525dce65525dce65525dce65525dce65525dce65525dce65525dce65525dce65525dce65525dce65525dce65525dce65525dce65525d ..."
         ],
         false
      ],
      [
         "TF",
         [
            1300,
            "**************************************************************** ..."
         ],
         0,
         false,
         0,
         "33ece872",
         null,
         null,
         false
      ],
      [
         "TO",
         [
            1308,
            "00fe051433ece87219c6c25819c6c25819c6c25819c6c25819c6c25819c6c25819c6c25819c6c25819c6c25819c6c25819c6c25819c6c25819c6c25819c6c258 ..."
         ],
         false
      ],
      [
         "TF",
         [
            1300,
            "**************************************************************** ..."
         ],
         0,
         false,
         0,
         "b716ded1",
         null,
         null,
         false
      ],
      [
         "TO",
         [
            1308,
            "00fe0514b716ded19d3cf4fb9d3cf4fb9d3cf4fb9d3cf4fb9d3cf4fb9d3cf4fb9d3cf4fb9d3cf4fb9d3cf4fb9d3cf4fb9d3cf4fb9d3cf4fb9d3cf4fb9d3cf4fb ..."
         ],
         false
      ],
      [
         "TF",
         [
            1300,
            "**************************************************************** ..."
         ],
         0,
         false,
         0,
         "24ef4903",
         null,
         null,
         false
      ],
      [
         "TO",
         [
            1308,
            "00fe051424ef49030ec563290ec563290ec563290ec563290ec563290ec563290ec563290ec563290ec563290ec563290ec563290ec563290ec563290ec56329 ..."
         ],
         false
      ],
      [
         "TF",
         [
            536,
            "**************************************************************** ..."
         ],
         0,
         true,
         0,
         "99136df3",
         null,
         null,
         false
      ],
      [
         "TO",
         [
            544,
            "80fe021899136df3b33947d9b33947d9b33947d9b33947d9b33947d9b33947d9b33947d9b33947d9b33947d9b33947d9b33947d9b33947d9b33947d9b33947d9 ..."
         ],
         false
      ],
      [
         "KL",
         10
      ],
      [
         "RO",
         [
            65536,
            "817f00000000000100002a2a2a2a2a2a2a2a2a2a2a2a2a2a2a2a2a2a2a2a2a2a2a2a2a2a2a2a2a2a2a2a2a2a2a2a2a2a2a2a2a2a2a2a2a2a2a2a2a2a2a2a2a2a ..."
         ]
      ],
      [
         "RO",
         [
            10,
            "2a2a2a2a2a2a2a2a2a2a"
         ]
      ],
      [
         "RF",
         [
            65536,
            "**************************************************************** ..."
         ],
         1,
         true,
         0,
         false,
         null
      ],
      [
         "TF",
         [
            2,
            "0x03e8"
         ],
         8,
         true,
         0,
         "4815ba89",
         null,
         null,
         false
      ],
      [
         "TO",
         [
            8,
            "88824815ba894bfd"
         ],
         false
      ],
      [
         "RO",
         [
            4,
            "880203e8"
         ]
      ],
      [
         "RF",
         [
            2,
            "0x03e8"
         ],
         8,
         true,
         0,
         false,
         null
      ]
   ]
}