{
   "agent": "gws-server/sync/context_take_over",
   "behavior": "OK",
   "behaviorClose": "OK",
   "case": 331,
   "closedByMe": true,
   "createStats": true,
   "createWirelog": true,
   "description": "Send 1000 compressed messages each of payload size 16384, auto-fragment to 256 octets. Use default permessage-deflate offer.",
   "droppedByMe": false,
   "duration": 1143,
   "expectation": "Receive echo'ed messages (with payload as sent). Timeout case after 480 secs.",
   "expected": {},
   "expectedClose": {
      "closeCode": [
         1000
      ],
      "closedByMe": true,
      "requireClean": true
   },
   "failedByMe": false,
   "httpRequest": "GET /connect HTTP/1.1\r\nUser-Agent: AutobahnTestSuite/0.8.2-0.10.9\r\nHost: 127.0.0.1:8000\r\nUpgrade: WebSocket\r\nConnection: Upgrade\r\nPragma: no-cache\r\nCache-Control: no-cache\r\nSec-WebSocket-Key: 652m9D9hTRX7coF2nuwNGA==\r\nSec-WebSocket-Extensions: permessage-deflate; client_no_context_takeover; client_max_window_bits\r\nSec-WebSocket-Version: 13\r\n\r\n",
   "httpResponse": "HTTP/1.1 101 Switching Protocols\r\nUpgrade: websocket\r\nConnection: Upgrade\r\nSec-WebSocket-Extensions: permessage-deflate; client_no_context_takeover; server_max_window_bits=12; client_max_window_bits=12\r\nSec-WebSocket-Accept: OfQ3s3TMGjHuUctaXJ0Dtm6KemE=\r\n\r\n",
   "id": "12.2.12",
   "isServer": false,
   "localCloseCode": 1000,
   "localCloseReason": null,
   "received": [],
   "remoteCloseCode": 1000,
   "remoteCloseReason": null,
   "reportCompressionRatio": true,
   "reportTime": true,
   "result": "Ok, received all echo'ed messages in time.",
   "resultClose": "Connection was properly closed",
   "rxFrameStats": {
      "2": 1000,
      "8": 1
   },
   "rxOctetStats": {
      "4": 1,
      "257": 1,
      "11287": 1,
      "11314": 1,
      "11423": 1,
      "11469": 1,
      "11492": 1,
      "11610": 1,
      "11677": 1,
      "11742": 1,
      "11762": 1,
      "11834": 1,
      "11836": 1,
      "11921": 1,
      "11949": 1,
      "11980": 1,
      "12060": 1,
      "12121": 1,
      "12151": 1,
      "12239": 1,
      "12267": 1,
      "12300": 1,
      "12349": 1,
      "12390": 1,
      "12419": 1,
      "12451": 1,
      "12472": 1,
      "12506": 1,
      "12559": 1,
      "12588": 1,
      "12591": 1,
      "12681": 1,
      "12689": 1,
      "12708": 1,
      "12757": 1,
      "12786": 1,
      "12799": 1,
      "12852": 1,
      "12865": 1,
      "12872": 1,
      "12876": 1,
      "12883": 1,
      "12904": 1,
      "12925": 1,
      "12943": 1,
      "12959": 1,
      "12983": 1,
      "12990": 1,
      "13006": 1,
      "13007": 1,
      "13010": 1,
      "13025": 1,
      "13033": 1,
      "13050": 1,
      "13052": 1,
      "13061": 1,
      "13064": 2,
      "13066": 1,
      "13083": 1,
      "13101": 1,
      "13171": 1,
      "13173": 1,
      "13192": 1,
      "13203": 1,
      "13235": 1,
      "13241": 1,
      "13249": 1,
      "13328": 1,
      "13339": 1,
      "13433": 1,
      "13442": 1,
      "13478": 1,
      "13585": 1,
      "13644": 1,
      "13690": 1,
      "13843": 1,
      "13953": 1,
      "14043": 1,
      "14124": 1,
      "14169": 1,
      "14202": 1,
      "14243": 1,
      "14294": 1,
      "14341": 1,
      "14364": 1,
      "14374": 2,
      "14435": 1,
      "14446": 1,
      "14449": 1,
      "14461": 1,
      "14469": 1,
      "14497": 1,
      "14676": 1,
      "14680": 1,
      "14683": 2,
      "14688": 1,
      "14694": 1,
      "14710": 1,
      "14713": 1,
      "14723": 1,
      "14748": 1,
      "14767": 1,
      "14784": 1,
      "14789": 1,
      "14803": 1,
      "14817": 1,
      "14838": 1,
      "14878": 1,
      "14885": 1,
      "14890": 1,
      "14897": 2,
      "14903": 1,
      "14910": 1,
      "14917": 1,
      "14927": 1,
      "14934": 2,
      "14935": 1,
      "14939": 1,
      "14942": 1,
      "14943": 1,
      "14945": 1,
      "14949": 1,
      "14950": 1,
      "14968": 1,
      "14969": 1,
      "14975": 2,
      "14976": 1,
      "14980": 1,
      "14988": 1,
      "14989": 1,
      "15007": 2,
      "15016": 1,
      "15022": 1,
      "15032": 1,
      "15034": 1,
      "15037": 1,
      "15045": 2,
      "15049": 1,
      "15052": 1,
      "15057": 2,
      "15058": 1,
      "15059": 1,
      "15060": 1,
      "15062": 1,
      "15065": 1,
      "15067": 2,
      "15074": 1,
      "15077": 4,
      "15078": 1,
      "15079": 2,
      "15084": 1,
      "15088": 1,
      "15091": 1,
      "15092": 1,
      "15097": 2,
      "15102": 2,
      "15106": 1,
      "15108": 1,
      "15110": 2,
      "15111": 2,
      "15114": 2,
      "15118": 2,
      "15120": 2,
      "15123": 1,
      "15124": 1,
      "15126": 1,
      "15130": 1,
      "15133": 1,
      "15137": 2,
      "15139": 1,
      "15140": 1,
      "15142": 1,
      "15147": 1,
      "15148": 2,
      "15149": 1,
      "15150": 1,
      "15151": 1,
      "15158": 1,
      "15161": 1,
      "15167": 2,
      "15169": 1,
      "15175": 1,
      "15178": 1,
      "15182": 1,
      "15183": 2,
      "15186": 1,
      "15188": 1,
      "15192": 1,
      "15197": 2,
      "15211": 1,
      "15212": 1,
      "15213": 1,
      "15215": 2,
      "15220": 1,
      "15221": 1,
      "15223": 1,
      "15228": 1,
      "15229": 1,
      "15230": 1,
      "15232": 1,
      "15233": 1,
      "15234": 1,
      "15236": 2,
      "15237": 2,
      "15243": 1,
      "15253": 1,
      "15256": 1,
      "15263": 1,
      "15267": 1,
      "15268": 1,
      "15271": 1,
      "15273": 1,
      "15274": 1,
      "15276": 2,
      "15284": 1,
      "15285": 1,
      "15286": 1,
      "15302": 1,
      "15306": 1,
      "15309": 1,
      "15313": 1,
      "15323": 1,
      "15331": 1,
      "15333": 1,
      "15334": 1,
      "15336": 1,
      "15337": 1,
      "15338": 1,
      "15339": 1,
      "15341": 1,
      "15342": 1,
      "15343": 3,
      "15346": 1,
      "15355": 1,
      "15361": 1,
      "15372": 1,
      "15385": 1,
      "15422": 2,
      "15424": 1,
      "15436": 1,
      "15438": 1,
      "16394": 728
   },
   "started": "2024-01-18T07:32:04.095Z",
   "trafficStats": {
      "incomingCompressionRatio": 0.9671207885742188,
      "incomingOctetsAppLevel": 16384000,
      "incomingOctetsWebSocketLevel": 15845307,
      "incomingOctetsWireLevel": 15849307,
      "incomingWebSocketFrames": 1000,
      "incomingWebSocketMessages": 1000,
      "incomingWebSocketOverhead": 0.0002524406753368679,
      "outgoingCompressionRatio": 0.8669129028320313,
      "outgoingOctetsAppLevel": 16384000,
      "outgoingOctetsWebSocketLevel": 14203501,
      "outgoingOctetsWireLevel": 14650387,
      "outgoingWebSocketFrames": 55980,
      "outgoingWebSocketMessages": 1000,
      "outgoingWebSocketOverhead": 0.03146308786826572,
      "preopenIncomingOctetsWireLevel": 257,
      "preopenOutgoingOctetsWireLevel": 345
   },
   "txFrameStats": {
      "0": 54980,
      "2": 1000,
      "8": 1
   },
   "txOctetStats": {
      "6": 1,
      "7": 3,
      "8": 3,
      "9": 3,
      "10": 3,
      "11": 3,
      "12": 1,
      "13": 1,
      "14": 5,
      "15": 4,
      "16": 6,
      "17": 6,
      "18": 2,
      "19": 4,
      "20": 3,
      "21": 2,
      "22": 4,
      "23": 5,
      "24": 4,
      "25": 7,
      "26": 5,
      "27": 7,
      "28": 4,
      "29": 7,
      "30": 7,
      "31": 3,
      "32": 8,
      "33": 1,
      "34": 2,
      "35": 6,
      "36": 5,
      "37": 4,
      "38": 2,
      "39": 3,
      "40": 1,
      "41": 2,
      "42": 3,
      "43": 6,
      "44": 2,
      "45": 3,
      "46": 3,
      "47": 3,
      "48": 8,
      "49": 3,
      "50": 7,
      "51": 4,
      "52": 5,
      "53": 3,
      "54": 3,
      "55": 1,
      "56": 6,
      "57": 5,
      "58": 5,
      "59": 3,
      "60": 3,
      "61": 7,
      "62": 3,
      "64": 5,
      "65": 3,
      "66": 5,
      "67": 2,
      "68": 2,
      "69": 3,
      "70": 5,
      "71": 4,
      "72": 3,
      "73": 4,
      "74": 3,
      "75": 6,
      "76": 4,
      "77": 7,
      "79": 5,
      "80": 3,
      "81": 3,
      "82": 4,
      "83": 4,
      "84": 2,
      "85": 10,
      "86": 8,
      "87": 8,
      "88": 2,
      "89": 4,
      "90": 3,
      "91": 5,
      "92": 5,
      "93": 5,
      "94": 5,
      "95": 3,
      "96": 5,
      "97": 3,
      "98": 3,
      "99": 5,
      "100": 3,
      "101": 4,
      "102": 4,
      "103": 3,
      "104": 4,
      "105": 4,
      "106": 3,
      "107": 6,
      "108": 3,
      "109": 3,
      "110": 2,
      "111": 4,
      "112": 3,
      "113": 3,
      "114": 3,
      "115": 3,
      "116": 3,
      "117": 4,
      "118": 1,
      "119": 1,
      "120": 2,
      "122": 7,
      "123": 3,
      "124": 4,
      "125": 3,
      "126": 8,
      "127": 2,
      "128": 5,
      "129": 2,
      "130": 2,
      "131": 2,
      "134": 8,
      "135": 5,
      "136": 6,
      "137": 2,
      "138": 1,
      "139": 2,
      "140": 6,
      "141": 4,
      "142": 1,
      "143": 3,
      "144": 4,
      "146": 5,
      "147": 5,
      "148": 4,
      "149": 5,
      "150": 5,
      "151": 3,
      "152": 1,
      "153": 2,
      "154": 5,
      "155": 3,
      "156": 5,
      "157": 2,
      "159": 3,
      "160": 3,
      "161": 6,
      "162": 6,
      "163": 4,
      "164": 1,
      "165": 4,
      "166": 5,
      "167": 2,
      "168": 6,
      "169": 4,
      "170": 6,
      "171": 4,
      "172": 7,
      "173": 3,
      "174": 10,
      "175": 4,
      "176": 4,
      "177": 4,
      "178": 3,
      "179": 7,
      "180": 3,
      "181": 6,
      "182": 5,
      "183": 6,
      "184": 3,
      "185": 8,
      "186": 3,
      "187": 6,
      "188": 4,
      "189": 3,
      "190": 3,
      "191": 3,
      "192": 2,
      "193": 1,
      "194": 7,
      "195": 3,
      "196": 1,
      "197": 3,
      "198": 4,
      "199": 9,
      "200": 4,
      "201": 4,
      "202": 6,
      "203": 5,
      "204": 4,
      "205": 9,
      "206": 4,
      "207": 4,
      "208": 4,
      "209": 7,
      "210": 5,
      "211": 3,
      "212": 3,
      "213": 3,
      "214": 4,
      "215": 4,
      "216": 5,
      "217": 2,
      "218": 5,
      "219": 4,
      "220": 6,
      "221": 6,
      "222": 4,
      "223": 5,
      "224": 7,
      "225": 2,
      "226": 4,
      "227": 3,
      "228": 3,
      "229": 2,
      "230": 3,
      "231": 1,
      "232": 6,
      "233": 1,
      "234": 6,
      "235": 5,
      "236": 5,
      "237": 8,
      "238": 4,
      "239": 5,
      "240": 1,
      "241": 3,
      "242": 9,
      "243": 6,
      "244": 2,
      "245": 3,
      "246": 6,
      "247": 2,
      "248": 4,
      "249": 2,
      "250": 5,
      "251": 3,
      "252": 2,
      "253": 2,
      "254": 3,
      "255": 6,
      "256": 3,
      "257": 2,
      "258": 2,
      "259": 3,
      "260": 1,
      "261": 3,
      "262": 7,
      "263": 2,
      "264": 54980,
      "345": 1
   },
   "wasClean": true,
   "wasCloseHandshakeTimeout": false,
   "wasNotCleanReason": null,
   "wasOpenHandshakeTimeout": false,
   "wasServerConnectionDropTimeout": false,
   "wirelog": [
      [
         "TO",
         [
            345,
            "474554202f636f6e6e65637420485454502f312e310d0a557365722d4167656e743a204175746f6261686e5465737453756974652f302e382e322d302e31302e ..."
         ],
         false
      ],
      [
         "RO",
         [
            257,
            "485454502f312e312031303120537769746368696e672050726f746f636f6c730d0a557067726164653a20776562736f636b65740d0a436f6e6e656374696f6e ..."
         ]
      ],
      [
         "WLM",
         false
      ],
      [
         "TI",
         480
      ],
      [
         "WLM",
         true
      ],
      [
         "TF",
         [
            2,
            "0x03e8"
         ],
         8,
         true,
         0,
         "ba637691",
         null,
         null,
         false
      ],
      [
         "TO",
         [
            8,
            "8882ba637691b98b"
         ],
         false
      ],
      [
         "RO",
         [
            4,
            "880203e8"
         ]
      ],
      [
         "RF",
         [
            2,
            "0x03e8"
         ],
         8,
         true,
         0,
         false,
         null
      ]
   ]
}