{
   "agent": "gws/server@v1.6.10",
   "behavior": "OK",
   "behaviorClose": "OK",
   "case": 64,
   "closedByMe": true,
   "createStats": true,
   "createWirelog": true,
   "description": "Same as Case 5.19, but send all frames with SYNC = True.\n   Note, this does not change the octets sent in any way, only how the stream\n   is chopped up on the wire.",
   "droppedByMe": false,
   "duration": 1004,
   "expectation": "Same as Case 5.19. Implementations must be agnostic to how\n   octet stream is chopped up on wire (must be TCP clean).",
   "expected": {
      "OK": [
         [
            "pong",
            "pongme 1!"
         ],
         [
            "pong",
            "pongme 2!"
         ],
         [
            "message",
            "fragment1fragment2fragment3fragment4fragment5",
            false
         ]
      ]
   },
   "expectedClose": {
      "closeCode": [
         1000
      ],
      "closedByMe": true,
      "requireClean": true
   },
   "failedByMe": false,
   "httpRequest": "GET /connect HTTP/1.1\r\nUser-Agent: AutobahnTestSuite/0.8.2-0.10.9\r\nHost: 192.168.31.99:8000\r\nUpgrade: WebSocket\r\nConnection: Upgrade\r\nPragma: no-cache\r\nCache-Control: no-cache\r\nSec-WebSocket-Key: hrFlEueEnvgi+dr9i1FNZw==\r\nSec-WebSocket-Version: 13\r\n\r\n",
   "httpResponse": "HTTP/1.1 101 Switching Protocols\r\nUpgrade: websocket\r\nConnection: Upgrade\r\nSec-WebSocket-Accept: giV4TSIhc/mYzetxI0tWeSFOgn4=\r\n\r\n",
   "id": "5.20",
   "isServer": false,
   "localCloseCode": 1000,
   "localCloseReason": null,
   "received": [
      [
         "pong",
         "pongme 1!"
      ],
      [
         "pong",
         "pongme 2!"
      ],
      [
         "message",
         "fragment1fragment2fragment3fragment4fragment5",
         false
      ]
   ],
   "remoteCloseCode": 1000,
   "remoteCloseReason": null,
   "reportCompressionRatio": false,
   "reportTime": false,
   "result": "Actual events match at least one expected.",
   "resultClose": "Connection was properly closed",
   "rxFrameStats": {
      "1": 1,
      "8": 1,
      "10": 2
   },
   "rxOctetStats": {
      "4": 1,
      "11": 2,
      "47": 1,
      "129": 1
   },
   "started": "2023-09-09T00:13:05.340Z",
   "trafficStats": null,
   "txFrameStats": {
      "0": 4,
      "1": 1,
      "8": 1,
      "9": 2
   },
   "txOctetStats": {
      "8": 1,
      "15": 7,
      "251": 1
   },
   "wasClean": true,
   "wasCloseHandshakeTimeout": false,
   "wasNotCleanReason": null,
   "wasOpenHandshakeTimeout": false,
   "wasServerConnectionDropTimeout": false,
   "wirelog": [
      [
         "TO",
         [
            251,
            "474554202f636f6e6e65637420485454502f312e310d0a557365722d4167656e743a204175746f6261686e5465737453756974652f302e382e322d302e31302e ..."
         ],
         false
      ],
      [
         "RO",
         [
            129,
            "485454502f312e312031303120537769746368696e672050726f746f636f6c730d0a557067726164653a20776562736f636b65740d0a436f6e6e656374696f6e ..."
         ]
      ],
      [
         "TF",
         [
            9,
            "fragment1"
         ],
         1,
         false,
         0,
         "46ae9f66",
         null,
         null,
         true
      ],
      [
         "TO",
         [
            15,
            "018946ae9f6620dcfe012bcbf11277"
         ],
         true
      ],
      [
         "TF",
         [
            9,
            "fragment2"
         ],
         0,
         false,
         0,
         "87584c64",
         null,
         null,
         true
      ],
      [
         "TF",
         [
            9,
            "pongme 1!"
         ],
         9,
         true,
         0,
         "4f02ad06",
         null,
         null,
         true
      ],
      [
         "CT",
         1,
         null
      ],
      [
         "TO",
         [
            15,
            "008987584c64e12a2d03ea3d2210b5"
         ],
         true
      ],
      [
         "TO",
         [
            15,
            "89894f02ad063f6dc36122678d376e"
         ],
         true
      ],
      [
         "RO",
         [
            11,
            "8a09706f6e676d65203121"
         ]
      ],
      [
         "RF",
         [
            9,
            "pongme 1!"
         ],
         10,
         true,
         0,
         false,
         null
      ],
      [
         "CTE",
         null
      ],
      [
         "TF",
         [
            9,
            "fragment3"
         ],
         0,
         false,
         0,
         "566d0a38",
         null,
         null,
         true
      ],
      [
         "TO",
         [
            15,
            "0089566d0a38301f6b5f3b08644c65"
         ],
         true
      ],
      [
         "TF",
         [
            9,
            "fragment4"
         ],
         0,
         false,
         0,
         "79e070ba",
         null,
         null,
         true
      ],
      [
         "TF",
         [
            9,
            "pongme 2!"
         ],
         9,
         true,
         0,
         "9f482efc",
         null,
         null,
         true
      ],
      [
         "TF",
         [
            9,
            "fragment5"
         ],
         0,
         true,
         0,
         "84682bc4",
         null,
         null,
         true
      ],
      [
         "TI",
         1
      ],
      [
         "TO",
         [
            15,
            "008979e070ba1f9211dd14851ece4d"
         ],
         true
      ],
      [
         "TO",
         [
            15,
            "89899f482efcef27409bf22d0ecebe"
         ],
         true
      ],
      [
         "TO",
         [
            15,
            "808984682bc4e21a4aa3e90d45b0b1"
         ],
         true
      ],
      [
         "RO",
         [
            11,
            "8a09706f6e676d65203221"
         ]
      ],
      [
         "RF",
         [
            9,
            "pongme 2!"
         ],
         10,
         true,
         0,
         false,
         null
      ],
      [
         "RO",
         [
            47,
            "812d667261676d656e7431667261676d656e7432667261676d656e7433667261676d656e7434667261676d656e7435"
         ]
      ],
      [
         "RF",
         [
            45,
            "fragment1fragment2fragment3fragment4fragment5"
         ],
         1,
         true,
         0,
         false,
         null
      ],
      [
         "TF",
         [
            2,
            "0x03e8"
         ],
         8,
         true,
         0,
         "bdef92aa",
         null,
         null,
         false
      ],
      [
         "TO",
         [
            8,
            "8882bdef92aabe07"
         ],
         false
      ],
      [
         "RO",
         [
            4,
            "880203e8"
         ]
      ],
      [
         "RF",
         [
            2,
            "0x03e8"
         ],
         8,
         true,
         0,
         false,
         null
      ]
   ]
}